{
  "indexes": [
    {
      "collectionGroup": "content_items",
      "queryScope": "COLLECTION",
      "fields": [
        {
          "fieldPath": "userEmail",
          "order": "ASCENDING"
        },
        {
          "fieldPath": "scheduledDate",
          "order": "ASCENDING"
        }
      ]
    },
    {
      "collectionGroup": "tasks",
      "queryScope": "COLLECTION",
      "fields": [
        {
          "fieldPath": "task_type",
          "order": "ASCENDING"
        },
        {
          "fieldPath": "clientId",
          "order": "ASCENDING"
        },
        {
          "fieldPath": "completed_date",
          "order": "DESCENDING"
        }
      ]
    },
    {
      "collectionGroup": "instagram_reports",
      "queryScope": "COLLECTION",
      "fields": [
        {
          "fieldPath": "userId",
          "order": "ASCENDING"
        },
        {
          "fieldPath": "createdAt",
          "order": "DESCENDING"
        }
      ]
    },
    {
      "collectionGroup": "instagram_reports",
      "queryScope": "COLLECTION",
      "fields": [
        {
          "fieldPath": "userId",
          "order": "ASCENDING"
        },
        {
          "fieldPath": "clientId",
          "order": "ASCENDING"
        },
        {
          "fieldPath": "startDate",
          "order": "DESCENDING"
        }
      ]
    },
    {
      "collectionGroup": "instagram_reports",
      "queryScope": "COLLECTION",
      "fields": [
        {
          "fieldPath": "clientId",
          "order": "ASCENDING"
        },
        {
          "fieldPath": "startDate",
          "order": "DESCENDING"
        }
      ]
    },
    {
      "collectionGroup": "leave_requests",
      "queryScope": "COLLECTION",
      "fields": [
        {
          "fieldPath": "employeeEmail",
          "order": "ASCENDING"
        },
        {
          "fieldPath": "submittedDate",
          "order": "DESCENDING"
        }
      ]
    },
    {
      "collectionGroup": "tasks",
      "queryScope": "COLLECTION",
      "fields": [
        {
          "fieldPath": "assigned_to",
          "order": "ASCENDING"
        },
        {
          "fieldPath": "createdAt",
          "order": "DESCENDING"
        }
      ]
    },
    {
      "collectionGroup": "post_log_monthly",
      "queryScope": "COLLECTION",
      "fields": [
        {
          "fieldPath": "clientId",
          "order": "ASCENDING"
        },
        {
          "fieldPath": "yearMonth",
          "order": "DESCENDING"
        }
      ]
    },
    {
      "collectionGroup": "content_items",
      "queryScope": "COLLECTION",
      "fields": [
        {
          "fieldPath": "userEmail",
          "order": "ASCENDING"
        },
        {
          "fieldPath": "calendarId",
          "order": "ASCENDING"
        },
        {
          "fieldPath": "scheduledDate",
          "order": "ASCENDING"
        }
      ]
    },
    {
      "collectionGroup": "feedback_chats",
      "queryScope": "COLLECTION",
      "fields": [
        {
          "fieldPath": "userEmail",
          "order": "ASCENDING"
        },
        {
          "fieldPath": "updatedAt",
          "order": "DESCENDING"
        }
      ]
    }
  ],
  "fieldOverrides": []
}